conftest.py
snipskit/__init__.py
snipskit/apps.py
snipskit/components.py
snipskit/config.py
snipskit/exceptions.py
snipskit/services.py
snipskit/tools.py
snipskit/decorators/__init__.py
snipskit/decorators/hermes.py
snipskit/decorators/mqtt.py
snipskit/hermes/__init__.py
snipskit/hermes/apps.py
snipskit/hermes/components.py
snipskit/hermes/decorators.py
snipskit/mqtt/__init__.py
snipskit/mqtt/apps.py
snipskit/mqtt/client.py
snipskit/mqtt/components.py
snipskit/mqtt/decorators.py
snipskit/mqtt/dialogue.py
snipskit-0.6.0.dist-info/LICENSE
snipskit-0.6.0.dist-info/METADATA
snipskit-0.6.0.dist-info/WHEEL
snipskit-0.6.0.dist-info/top_level.txt
snipskit-0.6.0.dist-info/RECORD
