Metadata-Version: 2.1
Name: snipskit
Version: 0.6.0
Summary: A library to help create apps for the voice assistant Snips
Home-page: https://github.com/koenvervloesem/snipskit
Author: Koen Vervloesem
Author-email: koen@vervloesem.eu
License: MIT
Platform: UNKNOWN
Classifier: Development Status :: 3 - Alpha
Classifier: Intended Audience :: Developers
Classifier: License :: OSI Approved :: MIT License
Classifier: Operating System :: POSIX
Classifier: Operating System :: Unix
Classifier: Programming Language :: Python
Classifier: Programming Language :: Python :: 3 :: Only
Classifier: Programming Language :: Python :: 3.5
Classifier: Programming Language :: Python :: 3.6
Classifier: Programming Language :: Python :: 3.7
Classifier: Programming Language :: Python :: Implementation :: CPython
Classifier: Topic :: Software Development :: Libraries
Requires-Dist: psutil
Requires-Dist: toml
Provides-Extra: hermes
Requires-Dist: hermes-python (>=0.3.3) ; extra == 'hermes'
Provides-Extra: mqtt
Requires-Dist: paho-mqtt ; extra == 'mqtt'
